kordesii/__init__.py
kordesii/cli.py
kordesii/core.py
kordesii/decoder.py
kordesii/ida_client.py
kordesii/ida_server.py
kordesii/logutil.py
kordesii/processors.py
kordesii/registry.py
kordesii/reporter.py
kordesii/serialization.py
kordesii/tester.py
kordesii/config/__init__.py
kordesii/config/log_config.yml
kordesii/decoders/Sample.py
kordesii/decoders/StackStringsNG.py
kordesii/decoders/__init__.py
kordesii/decoders/stack_string.py
kordesii/decoders/tests/Sample.json
kordesii/decoders/tests/strings.c
kordesii/decoders/tests/strings.exe
kordesii/decoders/tests/strings_arm
kordesii/tools/__init__.py
kordesii/tools/server/__init__.py
kordesii/tools/server/server.py
kordesii/tools/server/static/style.css
kordesii/tools/server/templates/base.html
kordesii/tools/server/templates/decoders.html
kordesii/tools/server/templates/results.html
kordesii/tools/server/templates/upload.html
kordesii/utils/__init__.py
kordesii/utils/decoderutils.py
kordesii/utils/flowchart.py
kordesii/utils/function_creator.py
kordesii/utils/functions.py
kordesii/utils/ida_re.py
kordesii/utils/segments.py
kordesii/utils/strings.py
kordesii/utils/tracing.py
kordesii/utils/utils.py
kordesii/utils/yara.py
kordesii/utils/function_tracing/__init__.py
kordesii/utils/function_tracing/actions.py
kordesii/utils/function_tracing/constants.py
kordesii/utils/function_tracing/cpu_context.py
kordesii/utils/function_tracing/emulator.py
kordesii/utils/function_tracing/exceptions.py
kordesii/utils/function_tracing/flowchart.py
kordesii/utils/function_tracing/function_tracer.py
kordesii/utils/function_tracing/functions.py
kordesii/utils/function_tracing/instruction.py
kordesii/utils/function_tracing/memory.py
kordesii/utils/function_tracing/objects.py
kordesii/utils/function_tracing/operands.py
kordesii/utils/function_tracing/registers.py
kordesii/utils/function_tracing/registry.py
kordesii/utils/function_tracing/utils.py
kordesii/utils/function_tracing/variables.py
kordesii/utils/function_tracing/ARM/__init__.py
kordesii-2.6.0.dist-info/LICENSE.txt
kordesii-2.6.0.dist-info/METADATA
kordesii-2.6.0.dist-info/WHEEL
kordesii-2.6.0.dist-info/entry_points.txt
kordesii-2.6.0.dist-info/top_level.txt
kordesii-2.6.0.dist-info/RECORD
