Metadata-Version: 2.1
Name: kordesii
Version: 2.6.0
Summary: A framework for decoding encoded strings and files in malware via IDA Pro IDAPython scripting.
Home-page: https://github.com/Defense-Cyber-Crime-Center/kordesii
Author: DC3
License: MIT
Keywords: malware,ida,idapro
Classifier: Development Status :: 5 - Production/Stable
Classifier: Intended Audience :: Developers
Classifier: License :: OSI Approved :: MIT License
Classifier: Programming Language :: Python :: 3
Classifier: Programming Language :: Python :: 3.6
Requires-Python: >=3.6
License-File: LICENSE.txt
Requires-Dist: click
Requires-Dist: dill
Requires-Dist: numpy
Requires-Dist: pyelftools
Requires-Dist: pefile >=2019.4.18
Requires-Dist: pycryptodome
Requires-Dist: requests
Requires-Dist: Pyro4
Requires-Dist: pyyaml
Requires-Dist: tabulate
Requires-Dist: yara-python
Requires-Dist: ruamel.yaml >=0.16.12
Requires-Dist: setuptools
Requires-Dist: six
Requires-Dist: flask
Requires-Dist: pygments
Provides-Extra: testing
Requires-Dist: pytest >=3.0.0 ; extra == 'testing'
Requires-Dist: pytest-console-scripts ; extra == 'testing'
